grpcgreeter
